scalene_mcp/__init__.py
scalene_mcp/analyzer.py
scalene_mcp/comparator.py
scalene_mcp/config.py
scalene_mcp/logging.py
scalene_mcp/models.py
scalene_mcp/parser.py
scalene_mcp/profiler.py
scalene_mcp/recommender.py
scalene_mcp/server.py
scalene_mcp/storage.py
scalene_mcp/utils.py
scalene_mcp-0.1.0.dist-info/METADATA
scalene_mcp-0.1.0.dist-info/WHEEL
scalene_mcp-0.1.0.dist-info/entry_points.txt
scalene_mcp-0.1.0.dist-info/RECORD
