Metadata-Version: 2.4
Name: scalene-mcp
Version: 0.1.0
Summary: FastMCP server providing LLM-optimized access to Scalene profiler
Author-email: Paul <paul@example.com>
Keywords: llm,mcp,performance,profiler,scalene
Classifier: Development Status :: 3 - Alpha
Classifier: Intended Audience :: Developers
Classifier: Programming Language :: Python :: 3.10
Classifier: Programming Language :: Python :: 3.11
Classifier: Programming Language :: Python :: 3.12
Classifier: Programming Language :: Python :: 3.13
Requires-Python: >=3.10
Requires-Dist: fastmcp<3.0.0,>=2.0.0
Requires-Dist: pydantic-settings>=2.0.0
Requires-Dist: pydantic>=2.11.7
Requires-Dist: rich>=13.9.4
Requires-Dist: scalene>=1.5.45
